[
  {
    "category_name": "AGROCHEMICALS",
    "company_name": "TYRONE AGROCHEMICALS PVT. LTD.",
    "address": "Jay Ashapura Industrial Estate, B/h. Ruda Nagar Transport, Ahmedabad Highway, Kuvavda Road, Anandpar - 360003",
    "contacts": [
      { "name": "Udaykumar D. Hinsu", "mobile": "9879656781" },
      { "name": "Hitesh M. Ghodasara", "mobile": "9879656783" }
    ],
    "email": ["tyroneagrochemicals@gmail.com"],
    "phone": ["9879656784"],
    "product_details": "Agro Chemicals",
    "brand": ""
  },
  {
    "category_name": "AGRI. MACHINERY & EQPT",
    "company_name": "A. T. N. ENTERPRISE",
    "address": "Kuvadva, GIDC Plot No.9, Rajkot-Ahmedabad Highway, Kuvavda Road, Rajkot - 360023",
    "contacts": [
      { "name": "Naimish J. Badani", "mobile": "9879522198" }
    ],
    "email": ["atnenterprise@yahoo.com"],
    "phone": [],
    "product_details": "Exporter",
    "brand": ""
  },
  {
    "category_name": "AGRI. MACHINERY & EQPT",
    "company_name": "ACMOCON SILEX",
    "address": "829, Star Plaza, Phulchhab Chowk, Rajkot - 360001",
    "contacts": [
      { "name": "Viral A. Ukani", "mobile": "9825629609" },
      { "name": "Prakashkumar S. Ukani", "mobile": "9687114466" }
    ],
    "email": [],
    "phone": ["2459244"],
    "product_details": "Agriculture Prod. Trading & Export",
    "brand": ""
  },
  {
    "category_name": "AGRI. MACHINERY & EQPT",
    "company_name": "ATLANTIS AGRITECH PVT. LTD.",
    "address": "Plot No. 36, Galaxy Industrial Estate, Shapar (Veraval) - 360024",
    "contacts": [
      { "name": "Rasiklal M. Sureja", "mobile": "7698400580" }
    ],
    "email": [],
    "phone": [],
    "product_details": "Agriculture Equipment, Manufacture",
    "brand": ""
  },
  {
    "category_name": "AGRI. MACHINERY & EQPT",
    "company_name": "B. R. & COMPANY",
    "address": "A/52, Market Yard, Bedi Gam, Rajkot",
    "contacts": [
      { "name": "Pratik Bipinbhai Patel", "mobile": "9824210541" },
      { "name": "Bipinbhai C. Patel", "mobile": "9824750042" }
    ],
    "email": ["bipinc1959@gmail.com"],
    "phone": [],
    "product_details": "Agri Product Trading",
    "brand": ""
  },
  {
    "category_name": "AGRI. MACHINERY & EQPT",
    "company_name": "BAJRANG HYDRAULIC SPARES",
    "address": "Shed No. 3, Plot No. 8, Silver Industries Area, Opp. Krishna Park, Gondal Road, Kothariya, Rajkot - 360004",
    "contacts": [
      { "name": "Vipulkumar L. Ashiyani", "mobile": "9909969288" }
    ],
    "email": ["bajranghydraulics_spare@yahoo.com"],
    "phone": ["9909969288"],
    "product_details": "Spare Parts",
    "brand": ""
  },
  {
    "category_name": "AGRI. MACHINERY & EQPT",
    "company_name": "BHOOMI AGRO INDUSTRIES",
    "address": "Plot No. G-1077, Road No A-1, Kishan Gate, Lodhika G.I.D.C., Metoda - 360021",
    "contacts": [
      { "name": "Sejalben K. Kathiria", "mobile": "9879171677" },
      { "name": "Kiranbhai M. Kathiria", "mobile": "9879171677" }
    ],
    "email": ["vismay@bhoomiagro.in"],
    "phone": [],
    "product_details": "Manufacturer & Exporter",
    "brand": ""
  },
  {
    "category_name": "AGRI. MACHINERY & EQPT",
    "company_name": "CAPTAIN POLY PLAST LTD.",
    "address": "UI-25, Royal Complex, Bhutkhana Chowk, Dhebar Road, Rajkot",
    "contacts": [
      { "name": "Rameshbhai D. Khichadia", "mobile": "9825075892" },
      { "name": "Gopalbhai D. Khichadia", "mobile": "9825075809" }
    ],
    "email": ["info@captainpolyplast.in"],
    "phone": ["2226361"],
    "product_details": "Agri. Machinery And Eqpt.",
    "brand": ""
  },
  {
    "category_name": "AGRI. MACHINERY & EQPT",
    "company_name": "CAPTAIN TRACTORS PVT. LTD.",
    "address": "15th Floor, South Block, Twinstar Building, 150 Feet Ring Road, Nr. Nana Mava Circle, Rajkot",
    "contacts": [
      { "name": "Rajeshbhai G. Movaliya", "mobile": "9033905500" },
      { "name": "Kailashbhai G. Mehta", "mobile": "9512032521" }
    ],
    "email": ["info@captaintractors.com"],
    "phone": ["02827252547", "02812240501"],
    "product_details": "Manufacturers Of Compact Tractor And Agricultural Equipment",
    "brand": ""
  },
  {
    "category_name": "AGRI. MACHINERY & EQPT",
    "company_name": "DEVHARI ENTERPRISE",
    "address": "Ambassy Tower, 4th Floor, Opp. Jubilee Garden, Jawahar Road, Rajkot",
    "contacts": [
      { "name": "Shri Narendra N. Davda", "mobile": "9377777761" },
      { "name": "Shri Nileshbhai H. Kothari", "mobile": "" }
    ],
    "email": [],
    "phone": ["2222991"],
    "product_details": "Agriculture Prod. Trading & Export",
    "brand": ""
  },
  {
    "category_name": "AGRI. MACHINERY & EQPT",
    "company_name": "FARMWORLD AGROTECH PVT. LTD.",
    "address": "Plot No.373, Road-IX, Khirasara Industrial Estate, Vill. Khirasara (Ramnaji), Tal. Lodhika, Rajkot",
    "contacts": [
      { "name": "Rameshbhai Tanti", "mobile": "8000505205" },
      { "name": "Dhaval Tanti", "mobile": "9879526190" }
    ],
    "email": ["dhavaltanti@farmworld.in", "info@farmworld.in"],
    "phone": [],
    "product_details": "Manufacturer & Exporter",
    "brand": ""
  },
  {
    "category_name": "AGRI. MACHINERY & EQPT",
    "company_name": "GRINDING MILL PRODUCTS",
    "address": "Survey No.246/3, Bhoomi Industrial Area, Nr. Divine Machine Tools, B/h. Welder Engineering, Dist. Rajkot, Veraval (Shapar) - 360024",
    "contacts": [
      { "name": "Vijaybhai Bhimjibhai Rathod", "mobile": "9824213011" }
    ],
    "email": ["milking_highfly@yahoo.co.in"],
    "phone": [],
    "product_details": "Manufacturer & Exporter",
    "brand": ""
  },
  {
    "category_name": "AGRI. MACHINERY & EQPT",
    "company_name": "IDOL POLYTECH PVT. LTD.",
    "address": "Plot No.2, RK Industrial Zone-8, Survey No.11/P1, Ranpur (Navagam), Wankaner, Kuvavda Chowkdi, Kuvavda Road, Rajkot - 360003",
    "contacts": [
      { "name": "Kantilal N. Vadodariya", "mobile": "9925255255" },
      { "name": "Jitendra C. Vadodariya", "mobile": "9825397598" }
    ],
    "email": ["hdpe@idolpipe.com", "account@idolpolytech.com"],
    "phone": ["9925255255"],
    "product_details": "Manufacturers",
    "brand": ""
  },
  {
    "category_name": "AGRI. MACHINERY & EQPT",
    "company_name": "JOLLY AGRI EXIM PVT. LTD.",
    "address": "D-307, The Imperial Heights, 3rd Floor, Opp. Big Bazar, 150 Ft. Ring Road, Kalawad Road, Rajkot",
    "contacts": [
      { "name": "Shri Jolly V. Halani", "mobile": "9825119214" },
      { "name": "Niloferben J. Halani", "mobile": "9825219214" }
    ],
    "email": ["director@jollycotton.in"],
    "phone": [],
    "product_details": "Export",
    "brand": ""
  },
  {
    "category_name": "AGRI. MACHINERY & EQPT",
    "company_name": "KEDARNATH FOOD INC",
    "address": "Revenue Survey No.159, Paik-1, Opp. Fishfa Agri World, Kuvavda-Wankaner Road, Sanosara, Rajkot",
    "contacts": [
      { "name": "Nagjibhai K. Limbasiya", "mobile": "9725864666" },
      { "name": "Yatin N. Limbasiya", "mobile": "9724780606" }
    ],
    "email": ["kedarnathfoodinc2019@gmail.com"],
    "phone": ["9724780606"],
    "product_details": "Manufacturer Of Agriculture Products",
    "brand": ""
  }
]